opp_net/__init__.py
opp_net/account_link.py
opp_net/acme.py
opp_net/auth.py
opp_net/client.py
opp_net/cloud_api.py
opp_net/cloudhooks.py
opp_net/const.py
opp_net/google_report_state.py
opp_net/iot.py
opp_net/iot_base.py
opp_net/remote.py
opp_net/thingtalk.py
opp_net/utils.py
opp_net/voice.py
opp_net-0.1.0.dist-info/LICENSE
opp_net-0.1.0.dist-info/METADATA
opp_net-0.1.0.dist-info/WHEEL
opp_net-0.1.0.dist-info/top_level.txt
opp_net-0.1.0.dist-info/RECORD
